{
  "ma_nganh": 7140101,
  "ten_nganh": "Giáo dục học",
  "ten_chuong_trinh": "Giáo dục học",
  "nam_ban_hanh": 2020,
  "khoa": "Khoa học giáo dục",
  "nam_tuyen_sinh": "2021 - Khoá 47",
  "ma_chuong_trinh": 7140101,
  "links": {
    "chuan_dau_ra": "https://drive.google.com/file/d/1_KWzr6VFD2oJoEqsyKGcJq1kE0aBNLtH/view?usp=sharing",
    "chuong_trinh_khung": "https://drive.google.com/file/d/1_KWzr6VFD2oJoEqsyKGcJq1kE0aBNLtH/view?usp=sharing",
    "quyet_dinh": "https://drive.google.com/open?id=1_OpnVo5_BXmBJGxLbbjJdmClg1-vOVoy&usp=drive_fs"
  }
}